bifrost_bsx_tools/__init__.py
bifrost_bsx_tools/core.py
bifrost_bsx_tools-0.0.4.dist-info/LICENSE.txt
bifrost_bsx_tools-0.0.4.dist-info/METADATA
bifrost_bsx_tools-0.0.4.dist-info/WHEEL
bifrost_bsx_tools-0.0.4.dist-info/top_level.txt
bifrost_bsx_tools-0.0.4.dist-info/RECORD
