Metadata-Version: 2.1
Name: bifrost-bsx-tools
Version: 0.0.4
Summary: Extract time series from Bifrost BSX files as pandas DataFrame.
Author-email: Valentin Bauer <valentin.bauer@tuwien.ac.at>
License: Copyright (c) 2023 Valentin Bauer
Project-URL: Homepage, https://github.com/va-li/bifrost-bsx-tools
Project-URL: Bug Tracker, https://github.com/va-li/bifrost-bsx-tools/issues
Project-URL: Bifrost, http://bifrost.siemens.com
Keywords: bifrost,bsx
Classifier: Development Status :: 3 - Alpha
Classifier: Programming Language :: Python :: 3
Classifier: License :: OSI Approved :: MIT License
Classifier: Operating System :: OS Independent
Requires-Python: >=3.7
License-File: LICENSE.txt
Requires-Dist: bifrost-common-py
Requires-Dist: pandas
Requires-Dist: pyyaml
